{
  "radionice": [
    {
      "id": "radionica_1",
      "ime": "React radionica",
      "datum": "01.01.2025",
      "predavac": "Lorem Ipsumić",
      "opis": "Uvodni tečaj za korištenje React-a.",
      "broj_prijava": 0
    },
    {
      "id": "radionica_2",
      "ime": "Express js tečaj",
      "datum": "01.02.2025",
      "predavac": "Ipsum loremić",
      "opis": "Uvodni tečaj za korištenje Express js-a.",
      "broj_prijava": 0
    },
    {
      "id": "radionica_3",
      "ime": "PHP radionica",
      "datum": "01.03.2025",
      "predavac": "Foobar Quux",
      "opis": "Uvodni tečaj za korištenje PHP-a.",
      "broj_prijava": 0
    },
    {
      "id": "radionica_4",
      "ime": ".Net radionica",
      "datum": "2024-01-07",
      "predavac": "Lorem Ipsumić",
      "opis": "Uvodni tečaj za korištenje .Net-a",
      "broj_prijava": 0
    }
  ],
  "predavaci": [
    {
      "id": "predavac_1",
      "ime": "Lorem Ipsumić",
      "biografija": "Lorem ipsum dolor sit amet, consectetur adipiscing elit, sed do eiusmod tempor incididunt ut labore et dolore magna aliqua.",
      "organizacija": "Digitalna Dalmacija"
    },
    {
      "id": "predavac_2",
      "ime": "Ipsum Loremić",
      "biografija": "Ut enim ad minim veniam, quis nostrud exercitation ullamco laboris nisi ut aliquip ex ea commodo consequat.",
      "organizacija": "Analogna Dalmacija"
    },
    {
      "id": "predavac_3",
      "ime": "Foobar Quux\t",
      "biografija": "Duis aute irure dolor in reprehenderit in voluptate velit esse cillum dolore eu fugiat nulla pariatur.",
      "organizacija": "Digitalna Dalmacija"
    }
  ],
  "organizacije": [
    {
      "id": "organizacija_1",
      "ime": "Digitalna Dalmacija",
      "opis": "Lorem ipsum dolor sit amet, consectetur adipiscing elit, sed do eiusmod tempor incididunt ut labore et dolore magna aliqua.",
      "radionice": [
        "React radionica",
        "PHP radionica"
      ]
    },
    {
      "id": "organizacija_2",
      "ime": "Analogna Dalmacija",
      "opis": "Eros donec ac odio tempor orci dapibus. Eget nullam non nisi est. Massa eget egestas purus viverra accumsan.",
      "radionice": [
        "Express js tečaj"
      ]
    }
  ],
  "tezine": [
    {
      "id": "junior",
      "ime": "Junior"
    },
    {
      "id": "mid",
      "ime": "Mid"
    },
    {
      "id": "senior",
      "ime": "Senior"
    }
  ],
  "teme": [
    {
      "id": "react",
      "ime": "React"
    },
    {
      "id": "express",
      "ime": "Express"
    },
    {
      "id": "next_js",
      "ime": "Next.js"
    }
  ]
}